pyconvertdigits/__init__.py
pyconvertdigits-0.0.2.dist-info/LICENSE.txt
pyconvertdigits-0.0.2.dist-info/METADATA
pyconvertdigits-0.0.2.dist-info/WHEEL
pyconvertdigits-0.0.2.dist-info/top_level.txt
pyconvertdigits-0.0.2.dist-info/RECORD
