Metadata-Version: 2.1
Name: pyconvertdigits
Version: 0.0.2
Summary: It is one of the useful module that can help you to convert English int to other languages
Home-page: https://github.com/towsefnafe/
Author: Towsef Hassan Nafe
Author-email: towsef.nafe@gmail.com
License: UNKNOWN
Platform: UNKNOWN
Classifier: Programming Language :: Python :: 3
Classifier: License :: OSI Approved :: MIT License
Classifier: Operating System :: OS Independent
